{
  "title": "AI Beyond Hype: Transforming Industries and Everyday Life in 2026",
  "slug": "ai-beyond-hype-transforming-industries-and-everyday-life-2026",
  "category": "Artificial Intelligence",
  "content": "## The Evolution of Artificial Intelligence: From Novelty to Necessity\n\nArtificial Intelligence has moved far beyond the experimental labs and tech demos. In 2026, AI is not just a tool but a fundamental layer of our digital infrastructure. From healthcare to entertainment, its influence is pervasive, often invisible, and deeply transformative. This article explores how AI is reshaping industries and daily experiences, offering both opportunities and challenges that we must navigate thoughtfully.\n\n## AI in Healthcare: Saving Lives with Precision\n\nOne of the most profound impacts of AI is in healthcare. Machine learning models now assist in diagnosing diseases with accuracy that rivals—and sometimes surpasses—human experts. For instance, AI-powered imaging systems can detect early signs of cancer, cardiovascular issues, and neurological disorders from scans, enabling earlier interventions. Beyond diagnostics, AI drives personalized medicine by analyzing genetic data to tailor treatments to individual patients. Drug discovery, once a decade-long process, is being accelerated by AI algorithms that predict molecular interactions, leading to faster development of new therapies.\n\n## AI in Business: Driving Efficiency and Innovation\n\nIn the corporate world, AI is the engine behind smarter decision-making. Predictive analytics help companies forecast market trends, optimize supply chains, and manage inventory with unprecedented precision. Customer service has been revolutionized by AI chatbots that handle complex queries, while natural language processing (NLP) enables sentiment analysis to gauge public opinion. Moreover, AI-augmented development—as discussed in [The New Era of Programming: Mastering AI-Augmented Development](/blog/new-era-programming-mastering-ai-augmented-development)—is empowering developers to write cleaner code faster, reducing bugs and accelerating deployment cycles.\n\n### Intelligent Automation in Manufacturing\n\nManufacturing is experiencing a renaissance through AI-driven robotics. Smart factories use computer vision for quality control, predictive maintenance to minimize downtime, and collaborative robots (cobots) that work alongside humans. This shift not only increases productivity but also enhances worker safety by automating dangerous tasks.\n\n## AI in Everyday Life: The Invisible Assistant\n\nFor the average person, AI is woven into daily routines, often without explicit notice. Smart assistants manage calendars, control home devices, and provide real-time traffic updates. Recommendation algorithms personalize content on streaming platforms, while AI filters spam from emails and suggests replies. Even more subtly, ambient intelligence—a concept explored in [The Rise of Ambient Intelligence: A Seamless Future](/blog/the-rise-of-ambient-intelligence-a-seamless-future)—creates environments that adapt to human needs, from adjusting lighting to predicting preferences.\n\n## The Ethical Imperative: Navigating Bias and Privacy\n\nWith great power comes great responsibility. AI systems are only as good as the data they are trained on, and biased data can lead to discriminatory outcomes. Ensuring fairness, transparency, and accountability in AI is a pressing challenge. Privacy concerns also loom large, as AI often requires vast amounts of personal data. Regulations like the EU AI Act are step in the right direction, but ongoing vigilance is needed to balance innovation with rights protection.\n\n## The Future of Work: Collaboration Between Humans and AI\n\nContrary to fears of mass unemployment, AI is more likely to augment human capabilities than replace them entirely. In fields like software development, AI handles repetitive tasks, allowing humans to focus on creativity and complex problem-solving. This collaborative dynamic is reshaping job roles and requiring new skill sets. As highlighted in [The Art of Clean Code: Mastering Maintainable Programming](/blog/the-art-of-clean-code-mastering-maintainable-programming), writing code that is both human-readable and AI-friendly is becoming a valuable skill.\n\n## Conclusion: Embracing an AI-Driven World\n\nArtificial Intelligence is no longer a futuristic concept; it is the present reality that touches every aspect of our lives. From revolutionizing healthcare and business to enhancing personal convenience, AI offers immense potential. However, harnessing its benefits requires careful ethical considerations and a commitment to inclusive development. As we continue to integrate AI deeper into our world, the key will be to steer its evolution toward positive outcomes for all.",
  "excerpt": "Discover how artificial intelligence is transforming industries from healthcare to manufacturing, and shaping everyday life in profound ways. Explore the opportunities and ethical challenges of AI in 2026.",
  "coverImage": "https://images.unsplash.com/photo-1677442136019-21780ecad995?auto=format&fit=crop&w=1200&q=80",
  "coverImageCredit": "Unsplash Photographer",
  "publishedAt": "2026-06-07T16:23:08.359Z"
}